fw_gear_utils/__init__.py
fw_gear_utils/config.py
fw_gear_utils/manifest.py
fw_gear_utils-0.1.1.dist-info/LICENSE
fw_gear_utils-0.1.1.dist-info/WHEEL
fw_gear_utils-0.1.1.dist-info/METADATA
fw_gear_utils-0.1.1.dist-info/RECORD
