Metadata-Version: 2.1
Name: fw-gear-utils
Version: 0.1.1
Summary: Flywheel common gear utilities
Home-page: https://gitlab.com/flywheel-io/public/gear-utils
License: MIT
Author: Flywheel
Author-email: support@flywheel.io
Requires-Python: >=3.8,<4.0
Classifier: License :: OSI Approved :: MIT License
Classifier: Programming Language :: Python :: 3
Classifier: Programming Language :: Python :: 3.8
Classifier: Programming Language :: Python :: 3.9
Requires-Dist: dotty-dict (>=1.3.0,<2.0.0)
Requires-Dist: flywheel-gears (>=0.2.1,<0.3.0)
Requires-Dist: jsonschema (>=3.2.0,<4.0.0)
Project-URL: Documentation, https://gitlab.com/flywheel-io/public/gear-utils
Project-URL: Repository, https://gitlab.com/flywheel-io/public/gear-utils
